odoo/addons/mobile_app_angular/README.rst
odoo/addons/mobile_app_angular/__init__.py
odoo/addons/mobile_app_angular/__manifest__.py
odoo/addons/mobile_app_angular/i18n/fr.po
odoo/addons/mobile_app_angular/i18n/mobile_app_angular.pot
odoo/addons/mobile_app_angular/readme/CONTRIBUTORS.rst
odoo/addons/mobile_app_angular/readme/DESCRIPTION.rst
odoo/addons/mobile_app_angular/static/description/icon.png
odoo/addons/mobile_app_angular/static/description/index.html
odoo/addons/mobile_app_angular/static/src/description/icon.png
odoo/addons/mobile_app_angular/static/src/img/favicon.ico
odoo/addons/mobile_app_angular/static/src/img/credits/logo-akretion.png
odoo/addons/mobile_app_angular/static/src/img/credits/logo-grap.png
odoo/addons/mobile_app_angular/static/src/img/credits/logo-oca.png
odoo/addons/mobile_app_angular/static/src/js/angular_odoo.js
odoo/addons/mobile_app_angular/static/src/lib/angular-cookies/angular-cookies.js
odoo/addons/mobile_app_angular/static/src/lib/angular-translate/angular-translate-loader-static-files.min.js
odoo/addons/mobile_app_angular/static/src/lib/angular-translate/angular-translate.min.js
odoo/addons/mobile_app_angular/static/src/lib/ionic/ionic.bundle.js
odoo/addons/mobile_app_angular/static/src/lib/ionic/ionic.css
odoo/addons/mobile_app_angular/static/src/lib/ionicons/css/ionicons.min.css
odoo/addons/mobile_app_angular/static/src/lib/ionicons/fonts/ionicons.ttf
odoo/addons/mobile_app_angular/static/src/lib/ionicons/fonts/ionicons.woff
odoo11_addon_mobile_app_angular-11.0.1.0.0.99.dev5.dist-info/METADATA
odoo11_addon_mobile_app_angular-11.0.1.0.0.99.dev5.dist-info/WHEEL
odoo11_addon_mobile_app_angular-11.0.1.0.0.99.dev5.dist-info/top_level.txt
odoo11_addon_mobile_app_angular-11.0.1.0.0.99.dev5.dist-info/RECORD
