Metadata-Version: 2.1
Name: odoo11-addon-mobile-app-angular
Version: 11.0.1.0.0.99.dev5
Summary: Provide Angular 1.1 framework in static folder
Home-page: https://github.com/OCA/stock-logistics-barcode
Author: GRAP,Akretion,Camptocamp,Odoo Community Association (OCA)
Author-email: support@odoo-community.org
License: AGPL-3
Platform: UNKNOWN
Classifier: Programming Language :: Python
Classifier: Framework :: Odoo
Classifier: Framework :: Odoo :: 11.0
Classifier: License :: OSI Approved :: GNU Affero General Public License v3
Classifier: Development Status :: 4 - Beta
Requires-Python: >=2.7, !=3.0.*, !=3.1.*, !=3.2.*, !=3.3.*, !=3.4.*
Requires-Dist: odoo11-addon-mobile-app-abstract
Requires-Dist: odoo <11.1dev,>=11.0a
